snowflake_connector/__init__.py
snowflake_connector/config.py
snowflake_connector/connector.py
snowflake_connector/exceptions.py
snowflake_connector/key_utils.py
snowflake_connector/pool.py
snowflake_connector/secrets.py
snowflake_connector/utils.py
snowflake_connector_helper-1.0.0.dist-info/licenses/LICENSE
snowflake_connector_helper-1.0.0.dist-info/METADATA
snowflake_connector_helper-1.0.0.dist-info/WHEEL
snowflake_connector_helper-1.0.0.dist-info/top_level.txt
snowflake_connector_helper-1.0.0.dist-info/RECORD
