Metadata-Version: 2.4
Name: snowflake-connector-helper
Version: 1.0.0
Summary: Internal Snowflake connector with PKCS#8 authentication for SignifyHealth Team
Author: Team of Noah A - SignifyHealth
License: INTERNAL USE LICENSE
Keywords: snowflake,database,internal,signifyhealth,noah-a,pkcs8
Classifier: Development Status :: 5 - Production/Stable
Classifier: Intended Audience :: Information Technology
Classifier: License :: Other/Proprietary License
Classifier: Operating System :: OS Independent
Classifier: Programming Language :: Python :: 3
Classifier: Programming Language :: Python :: 3.8
Classifier: Programming Language :: Python :: 3.9
Classifier: Programming Language :: Python :: 3.10
Classifier: Programming Language :: Python :: 3.11
Classifier: Programming Language :: Python :: 3.12
Classifier: Topic :: Database
Classifier: Topic :: Office/Business :: Financial :: Investment
Requires-Python: >=3.8
License-File: LICENSE
Requires-Dist: snowflake-connector-python>=3.0.0
Requires-Dist: pandas>=1.5.0
Requires-Dist: pydantic>=1.10.0
Requires-Dist: python-dotenv>=0.19.0
Requires-Dist: cryptography>=3.4.0
Provides-Extra: dev
Requires-Dist: pytest>=7.0.0; extra == "dev"
Requires-Dist: pytest-cov>=4.0.0; extra == "dev"
Provides-Extra: secrets
Requires-Dist: boto3>=1.26.0; extra == "secrets"
Requires-Dist: hvac>=1.0.0; extra == "secrets"
Dynamic: license-file
Dynamic: requires-python
